{
  "cooldown": 4,
  "cost": 1,
  "effects": [
    {
      "type": "hit_damage_step",
      "crit": true,
      "attack_type": "hit",
      "damage_types": [
        "physical"
      ],
      "min_base_damage": 7,
      "max_base_damage": 10,
      "weapon_type": "melee",
      "scale_properties": {
        "scale_added": 100,
        "scale_increased": 100,
        "scale_speed": 100
      }
    },
    {
      "type": "apply_effect",
      "effect": "crash_stun_effect"
    }
  ],
  "id": "crash_skill",
  "presentation": {
    "name": "Crash",
    "description": "a hard hitting attack that stuns the target"
  }
}